[{"abbr":"af","name":"Afghanistan","code":"+93","mask":"+93 00 000 0000"},{"abbr":"al","name":"Albania","code":"+355","mask":"+355 (000) 000 000"},{"abbr":"dz","name":"Algeria","code":"+213","mask":"+213 00 000 0000"},{"abbr":"ad","name":"Andorra","code":"+376","mask":"+376 000 000"},{"abbr":"ao","name":"Angola","code":"+244","mask":"+244 (000) 000 000"},{"abbr":"ag","name":"Antigua and Barbuda","code":"+1268","mask":"+1 (268) 000 0000"},{"abbr":"ar","name":"Argentina","code":"+54","mask":"+54 (000) 000 0000"},{"abbr":"am","name":"Armenia","code":"+374","mask":"+374 00 000 000"},{"abbr":"aw","name":"Aruba","code":"+297","mask":"+297 000 0000"},{"abbr":"au","name":"Australia","code":"+61","mask":"+61 0 0000 0000"},{"abbr":"at","name":"Austria","code":"+43","mask":"+43 (000) 000 0000"},{"abbr":"az","name":"Azerbaijan","code":"+994","mask":"+994 00 000 00 00"},{"abbr":"bs","name":"Bahamas","code":"+1242","mask":"+1 (242) 000 0000"},{"abbr":"bh","name":"Bahrain","code":"+973","mask":"+973 0000 0000"},{"abbr":"bd","name":"Bangladesh","code":"+880","mask":"+880 00 000 000"},{"abbr":"bb","name":"Barbados","code":"+1246","mask":"+1 (246) 000 0000"},{"abbr":"by","name":"Belarus","code":"+375","mask":"+375 (00) 000 00 00"},{"abbr":"be","name":"Belgium","code":"+32","mask":"+32 (000) 000 000"},{"abbr":"bz","name":"Belize","code":"+501","mask":"+501 000 0000"},{"abbr":"bj","name":"Benin","code":"+229","mask":"+229 00 00 0000"},{"abbr":"bt","name":"Bhutan","code":"+975","mask":"+975 0 000 000"},{"abbr":"bo","name":"Bolivia","code":"+591","mask":"+591 0 000 0000"},{"abbr":"ba","name":"Bosnia and Herzegovina","code":"+387","mask":"+387 00 0000"},{"abbr":"bw","name":"Botswana","code":"+267","mask":"+267 00 000 000"},{"abbr":"br","name":"Brazil","code":"+55","mask":"+55 (00) 90000 0000"},{"abbr":"io","name":"British Indian Ocean Territory","code":"+246","mask":"+246 000 0000"},{"abbr":"bn","name":"Brunei","code":"+673","mask":"+673 000 0000"},{"abbr":"bg","name":"Bulgaria","code":"+359","mask":"+359 (000) 000 000"},{"abbr":"bf","name":"Burkina Faso","code":"+226","mask":"+226 00 00 0000"},{"abbr":"bi","name":"Burundi","code":"+257","mask":"+257 00 00 0000"},{"abbr":"kh","name":"Cambodia","code":"+855","mask":"+855 00 000 000"},{"abbr":"cm","name":"Cameroon","code":"+237","mask":"+237 0000 0000"},{"abbr":"ca","name":"Canada","code":"+1","mask":"+1 (000) 000 0000"},{"abbr":"cv","name":"Cape Verde","code":"+238","mask":"+238 (000) 00 00"},{"abbr":"bq","name":"Caribbean Netherlands","code":"+599"},{"abbr":"cf","name":"Central African Republic","code":"+236","mask":"+236 00 00 0000"},{"abbr":"td","name":"Chad","code":"+235","mask":"+235 00 00 00 00"},{"abbr":"cl","name":"Chile","code":"+56","mask":"+56 0 0000 0000"},{"abbr":"cn","name":"China","code":"+86","mask":"+86 00 00000 00000"},{"abbr":"co","name":"Colombia","code":"+57","mask":"+57 (000) 000 0000"},{"abbr":"km","name":"Comoros","code":"+269","mask":"+269 00 00000"},{"abbr":"cd","name":"Congo","code":"+243","mask":"+243 (000) 000 000"},{"abbr":"cg","name":"Congo","code":"+242","mask":"+242 00 000 0000"},{"abbr":"cr","name":"Costa Rica","code":"+506","mask":"+506 0000 0000"},{"abbr":"ci","name":"Côte d’Ivoire","code":"+225","mask":"+225 00 000 000"},{"abbr":"hr","name":"Croatia","code":"+385","mask":"+385 00 000 000"},{"abbr":"cu","name":"Cuba","code":"+53","mask":"+53 0 000 0000"},{"abbr":"cw","name":"Curaçao","code":"+599","mask":"+599 000 0000"},{"abbr":"cy","name":"Cyprus","code":"+357","mask":"+357 00 000 000"},{"abbr":"cz","name":"Czech Republic","code":"+420","mask":"+420 (000) 000 000"},{"abbr":"dk","name":"Denmark","code":"+45","mask":"+45 00 00 00 00"},{"abbr":"dj","name":"Djibouti","code":"+253","mask":"+253 00 00 00 00"},{"abbr":"dm","name":"Dominica","code":"+1767","mask":"+1 (767) 000 0000"},{"abbr":"do","name":"Dominican Republic","code":"+1","mask":"+1 (849) 000 0000"},{"abbr":"ec","name":"Ecuador","code":"+593","mask":"+593 0 000 0000"},{"abbr":"eg","name":"Egypt","code":"+20","mask":"+20 (000) 000 0000"},{"abbr":"sv","name":"El Salvador","code":"+503","mask":"+503 00 00 0000"},{"abbr":"gq","name":"Equatorial Guinea","code":"+240","mask":"+240 00 000 0000"},{"abbr":"er","name":"Eritrea","code":"+291","mask":"+291 0 000 000"},{"abbr":"ee","name":"Estonia","code":"+372","mask":"+372 000 0000"},{"abbr":"et","name":"Ethiopia","code":"+251","mask":"+251 00 000 0000"},{"abbr":"fj","name":"Fiji","code":"+679","mask":"+679 00 00000"},{"abbr":"fi","name":"Finland","code":"+358","mask":"+358 (000) 000 00 00"},{"abbr":"fr","name":"France","code":"+33","mask":"+590 (000) 000 000"},{"abbr":"gf","name":"French Guiana","code":"+594","mask":"+594 00000 0000"},{"abbr":"pf","name":"French Polynesia","code":"+689","mask":"+689 00 00 00"},{"abbr":"ga","name":"Gabon","code":"+241","mask":"+241 0 00 00 00"},{"abbr":"gm","name":"Gambia","code":"+220","mask":"+220 (000) 00 00"},{"abbr":"ge","name":"Georgia","code":"+995","mask":"+995 (000) 000 000"},{"abbr":"de","name":"Germany","code":"+49","mask":"+49 000 000"},{"abbr":"gh","name":"Ghana","code":"+233","mask":"+233 (000) 000 000"},{"abbr":"gr","name":"Greece","code":"+30","mask":"+30 (000) 000 0000"},{"abbr":"gd","name":"Grenada","code":"+1473","mask":"+1 (473) 000 0000"},{"abbr":"gp","name":"Guadeloupe","code":"+590"},{"abbr":"gu","name":"Guam","code":"+1671","mask":"+1 (671) 000 0000"},{"abbr":"gt","name":"Guatemala","code":"+502","mask":"+502 0 000 0000"},{"abbr":"gn","name":"Guinea","code":"+224","mask":"+224 00 000 000"},{"abbr":"gw","name":"Guinea Bissau","code":"+245","mask":"+245 0 000000"},{"abbr":"gy","name":"Guyana","code":"+592","mask":"+592 000 0000"},{"abbr":"ht","name":"Haiti","code":"+509","mask":"+509 00 00 0000"},{"abbr":"hn","name":"Honduras","code":"+504","mask":"+504 0000 0000"},{"abbr":"hk","name":"Hong Kong","code":"+852","mask":"+852 0000 0000"},{"abbr":"hu","name":"Hungary","code":"+36","mask":"+36 (000) 000 000"},{"abbr":"is","name":"Iceland","code":"+354","mask":"+354 000 0000"},{"abbr":"in","name":"India","code":"+91","mask":"+91 (0000) 000 000"},{"abbr":"id","name":"Indonesia","code":"+62","mask":"+62 (800) 000 00 000"},{"abbr":"ir","name":"Iran","code":"+98","mask":"+98 (000) 000 0000"},{"abbr":"iq","name":"Iraq","code":"+964","mask":"+964 (000) 000 0000"},{"abbr":"ie","name":"Ireland","code":"+353","mask":"+353 (000) 000 000"},{"abbr":"il","name":"Israel","code":"+972","mask":"+972 0 000 0000"},{"abbr":"it","name":"Italy","code":"+39","mask":"+39 (000) 0000 000"},{"abbr":"jm","name":"Jamaica","code":"+1876","mask":"+1 (876) 000 0000"},{"abbr":"jp","name":"Japan","code":"+81","mask":"+81 (000) 000 000"},{"abbr":"jo","name":"Jordan","code":"+962","mask":"+962 0 0000 0000"},{"abbr":"kz","name":"Kazakhstan","code":"+7","mask":"+7 (700) 000 00 00"},{"abbr":"ke","name":"Kenya","code":"+254","mask":"+254 000 000000"},{"abbr":"ki","name":"Kiribati","code":"+686","mask":"+686 00 000"},{"abbr":"xk","name":"Kosovo","code":"+383"},{"abbr":"kw","name":"Kuwait","code":"+965","mask":"+965 0000 0000"},{"abbr":"kg","name":"Kyrgyzstan","code":"+996","mask":"+996 (000) 000 000"},{"abbr":"la","name":"Laos","code":"+856","mask":"+856 00 000 000"},{"abbr":"lv","name":"Latvia","code":"+371","mask":"+371 00 000 000"},{"abbr":"lb","name":"Lebanon","code":"+961","mask":"+961 0 000 000"},{"abbr":"ls","name":"Lesotho","code":"+266","mask":"+266 0 000 0000"},{"abbr":"lr","name":"Liberia","code":"+231","mask":"+231 00 000 000"},{"abbr":"ly","name":"Libya","code":"+218","mask":"+218 21 000 0000"},{"abbr":"li","name":"Liechtenstein","code":"+423","mask":"+423 (000) 000 0000"},{"abbr":"lt","name":"Lithuania","code":"+370","mask":"+370 (000) 00 000"},{"abbr":"lu","name":"Luxembourg","code":"+352","mask":"+352 (000) 000 000"},{"abbr":"mo","name":"Macau","code":"+853","mask":"+853 0000 0000"},{"abbr":"mk","name":"Macedonia","code":"+389","mask":"+389 00 000 000"},{"abbr":"mg","name":"Madagascar","code":"+261","mask":"+261 00 00 00000"},{"abbr":"mw","name":"Malawi","code":"+265","mask":"+265 0 0000 0000"},{"abbr":"my","name":"Malaysia","code":"+60","mask":"+60 0 000 000"},{"abbr":"mv","name":"Maldives","code":"+960","mask":"+960 000 0000"},{"abbr":"ml","name":"Mali","code":"+223","mask":"+223 00 00 0000"},{"abbr":"mt","name":"Malta","code":"+356","mask":"+356 0000 0000"},{"abbr":"mh","name":"Marshall Islands","code":"+692","mask":"+692 000 0000"},{"abbr":"mq","name":"Martinique","code":"+596","mask":"+596 (000) 00 00 00"},{"abbr":"mr","name":"Mauritania","code":"+222","mask":"+222 00 00 0000"},{"abbr":"mu","name":"Mauritius","code":"+230","mask":"+230 000 0000"},{"abbr":"mx","name":"Mexico","code":"+52","mask":"+52 00 00 0000"},{"abbr":"fm","name":"Micronesia","code":"+691","mask":"+691 000 0000"},{"abbr":"md","name":"Moldova","code":"+373","mask":"+373 0000 0000"},{"abbr":"mc","name":"Monaco","code":"+377","mask":"+377 00 000 000"},{"abbr":"mn","name":"Mongolia","code":"+976","mask":"+976 00 00 0000"},{"abbr":"me","name":"Montenegro","code":"+382","mask":"+382 00 000 000"},{"abbr":"ma","name":"Morocco","code":"+212","mask":"+212 00 0000 000"},{"abbr":"mz","name":"Mozambique","code":"+258","mask":"+258 00 000 000"},{"abbr":"mm","name":"Myanmar","code":"+95","mask":"+95 000 000"},{"abbr":"na","name":"Namibia","code":"+264","mask":"+264 00 000 0000"},{"abbr":"nr","name":"Nauru","code":"+674","mask":"+674 000 0000"},{"abbr":"np","name":"Nepal","code":"+977","mask":"+977 00 000 000"},{"abbr":"nl","name":"Netherlands","code":"+31","mask":"+31 00 000 0000"},{"abbr":"nc","name":"New Caledonia","code":"+687","mask":"+687 00 0000"},{"abbr":"nz","name":"New Zealand","code":"+64","mask":"+64 (000) 000 0000"},{"abbr":"ni","name":"Nicaragua","code":"+505","mask":"+505 0000 0000"},{"abbr":"ne","name":"Niger","code":"+227","mask":"+227 00 00 0000"},{"abbr":"ng","name":"Nigeria","code":"+234","mask":"+234 (000) 000 0000"},{"abbr":"kp","name":"North Korea","code":"+850","mask":"+850 0000 0000000000000"},{"abbr":"no","name":"Norway","code":"+47","mask":"+47 (000) 00 000"},{"abbr":"om","name":"Oman","code":"+968","mask":"+968 00 000 000"},{"abbr":"pk","name":"Pakistan","code":"+92","mask":"+92 (000) 000 0000"},{"abbr":"pw","name":"Palau","code":"+680","mask":"+680 000 0000"},{"abbr":"ps","name":"Palestine","code":"+970","mask":"+970 00 000 0000"},{"abbr":"pa","name":"Panama","code":"+507","mask":"+507 000 0000"},{"abbr":"pg","name":"Papua New Guinea","code":"+675","mask":"+675 (000) 00 000"},{"abbr":"py","name":"Paraguay","code":"+595","mask":"+595 (000) 000 000"},{"abbr":"pe","name":"Peru","code":"+51","mask":"+51 (000) 000 000"},{"abbr":"ph","name":"Philippines","code":"+63","mask":"+63 (000) 000 0000"},{"abbr":"pl","name":"Poland","code":"+48","mask":"+48 (000) 000 000"},{"abbr":"pt","name":"Portugal","code":"+351","mask":"+351 00 000 0000"},{"abbr":"pr","name":"Puerto Rico","code":"+1"},{"abbr":"qa","name":"Qatar","code":"+974","mask":"+974 0000 0000"},{"abbr":"re","name":"Réunion","code":"+262","mask":"+262 00000 0000"},{"abbr":"ro","name":"Romania","code":"+40","mask":"+40 00 000 0000"},{"abbr":"ru","name":"Russia","code":"+7","mask":"+7 (000) 000 00 00"},{"abbr":"rw","name":"Rwanda","code":"+250","mask":"+250 (000) 000 000"},{"abbr":"kn","name":"Saint Kitts and Nevis","code":"+1869","mask":"+1 (869) 000 0000"},{"abbr":"lc","name":"Saint Lucia","code":"+1758","mask":"+1 (758) 000 0000"},{"abbr":"vc","name":"Saint Vincent and the Grenadines","code":"+1784","mask":"+1 (784) 000 0000"},{"abbr":"ws","name":"Samoa","code":"+685","mask":"+685 00 0000"},{"abbr":"sm","name":"San Marino","code":"+378","mask":"+378 0000 000000"},{"abbr":"st","name":"São Tomé and Príncipe","code":"+239","mask":"+239 00 00000"},{"abbr":"sa","name":"Saudi Arabia","code":"+966","mask":"+966 0 000 0000"},{"abbr":"sn","name":"Senegal","code":"+221","mask":"+221 00 000 0000"},{"abbr":"rs","name":"Serbia","code":"+381","mask":"+381 00 000 0000"},{"abbr":"sc","name":"Seychelles","code":"+248","mask":"+248 0 000 000"},{"abbr":"sl","name":"Sierra Leone","code":"+232","mask":"+232 00 000000"},{"abbr":"sg","name":"Singapore","code":"+65","mask":"+65 0000 0000"},{"abbr":"sk","name":"Slovakia","code":"+421","mask":"+421 (000) 000 000"},{"abbr":"si","name":"Slovenia","code":"+386","mask":"+386 00 000 000"},{"abbr":"sb","name":"Solomon Islands","code":"+677","mask":"+677 00000"},{"abbr":"so","name":"Somalia","code":"+252","mask":"+252 0 000 000"},{"abbr":"za","name":"South Africa","code":"+27","mask":"+27 00 000 0000"},{"abbr":"kr","name":"South Korea","code":"+82","mask":"+82 00 000 0000"},{"abbr":"ss","name":"South Sudan","code":"+211","mask":"+211 00 000 0000"},{"abbr":"es","name":"Spain","code":"+34","mask":"+34 (000) 000 000"},{"abbr":"lk","name":"Sri Lanka","code":"+94","mask":"+94 00 000 0000"},{"abbr":"sd","name":"Sudan","code":"+249","mask":"+249 00 000 0000"},{"abbr":"sr","name":"Suriname","code":"+597","mask":"+597 000 000"},{"abbr":"sz","name":"Swaziland","code":"+268","mask":"+268 00 00 0000"},{"abbr":"se","name":"Sweden","code":"+46","mask":"+46 00 000 0000"},{"abbr":"ch","name":"Switzerland","code":"+41","mask":"+41 00 000 0000"},{"abbr":"sy","name":"Syria","code":"+963","mask":"+963 00 0000 000"},{"abbr":"tw","name":"Taiwan","code":"+886","mask":"+886 0000 0000"},{"abbr":"tj","name":"Tajikistan","code":"+992","mask":"+992 00 000 0000"},{"abbr":"tz","name":"Tanzania","code":"+255","mask":"+255 00 000 0000"},{"abbr":"th","name":"Thailand","code":"+66","mask":"+66 00 000 000"},{"abbr":"tl","name":"Timor Leste","code":"+670","mask":"+670 780 00000"},{"abbr":"tg","name":"Togo","code":"+228","mask":"+228 00 000 000"},{"abbr":"to","name":"Tonga","code":"+676","mask":"+676 00000"},{"abbr":"tt","name":"Trinidad and Tobago","code":"+1868","mask":"+1 (868) 000 0000"},{"abbr":"tn","name":"Tunisia","code":"+216","mask":"+216 00 000 000"},{"abbr":"tr","name":"Turkey","code":"+90","mask":"+90 (000) 000 0000"},{"abbr":"tm","name":"Turkmenistan","code":"+993","mask":"+993 0 000 0000"},{"abbr":"tv","name":"Tuvalu","code":"+688","mask":"+688 20000"},{"abbr":"ug","name":"Uganda","code":"+256","mask":"+256 (000) 000 000"},{"abbr":"ua","name":"Ukraine","code":"+380","mask":"+380 (00) 000 00 00"},{"abbr":"ae","name":"United Arab Emirates","code":"+971","mask":"+971 0 000 0000"},{"abbr":"gb","name":"United Kingdom","code":"+44"},{"abbr":"us","name":"United States","code":"+1","mask":"+1 (000) 000 0000"},{"abbr":"uy","name":"Uruguay","code":"+598","mask":"+598 0 000 00 00"},{"abbr":"uz","name":"Uzbekistan","code":"+998","mask":"+998 00 000 0000"},{"abbr":"vu","name":"Vanuatu","code":"+678","mask":"+678 00000"},{"abbr":"va","name":"Vatican City","code":"+39","mask":"+39 6 698 00000"},{"abbr":"ve","name":"Venezuela","code":"+58","mask":"+58 (000) 000 0000"},{"abbr":"vn","name":"Vietnam","code":"+84","mask":"+84 (000) 0000 000"},{"abbr":"ye","name":"Yemen","code":"+967","mask":"+967 00 000 000"},{"abbr":"zm","name":"Zambia","code":"+260","mask":"+260 00 000 0000"},{"abbr":"zw","name":"Zimbabwe","code":"+263","mask":"+263 0 000000"}]
